Workbook

Sheet Target Financials
B2: Company | C2: Revenue (£) | D2: Operating Profit / EBIT (£) | E2: EBITDA Derived (£) | F2: EBITDA Margin (%) | G2: Cash & Equivalents (£) | H2: Total Borrowings (£) | I2: Net Debt (£) | J2: Average Employees
B3: ParkingEye | C3: 61056000 | D3: 16742000 | E3: 28780000 | F3: 47.14 | G3: 5352000 | H3: 4126000 | I3: -1226000 | J3: 334
B4: TMA Group | C4: 22919421 | D4: 4616668 | E4: 7417435 | F4: 32.36 | G4: 8335949 | H4: 23008598 | I4: 14672649 | J4: 196
B5: Yellow Line Parking (AppyWay) | C5: 5200000 | D5: -250000 | E5: -50000 | F5: -1 | G5: 730440 | H5: 0 | I5: -730440 | J5: 37
B6: Ebbon Group | C6: 13656986 | D6: 1792977 | E6: 3261578 | F6: 23.9 | G6: 5226036 | H6: 6268005 | I6: -1041969 | J6: 55
B7: FleetCheck | C7: 4600000 | D7: 1150000 | E7: 1350000 | F7: 29.3 | G7: 875976 | H7: 0 | I7: -875976 | J7: 48
B8: Joju Charging | C8: 10095903 | D8: 209234 | E8: 232206 | F8: 2.3 | G8: 881536 | H8: 606635 | I8: 274901 | J8: 62
C10: Because TMA group includes bits I don’t want to buy I have to look at the entire holdcos financials
C11: The transaction will be structured either as a direct share purchase of the core operating subsidiary or via a structured asset carve-out to ensure the platform assumes zero legacy holding-company liabilities.
C13: If your platform only wants to buy the EV charging infrastructure network segment, you explain this in your narrative text. You write that the acquisition will be structured as a "Carve-Out Deal".
C14: Your private equity platform will only buy the EV contracts, technology assets, and engineering staff, leaving the traditional rooftop solar panel installation business with the original founders.
B1048556: =SUM(B1:B1048555) -> 0 | D1048556: =SUM(D1:D1048555) -> 24260879

Sheet CCA
B2: Segment | C2: Company Name + Ticker | D2: Exchnange | E2: Revenue (£m) | F2: Revenue Growth (Y-o-Y %) | G2: Market Cap (£m) | H2: Net Debt (£m) | I2: EBITDA (£m) | J2: Enterprise Value (£m) | K2: EV / Revenue | L2: EV / EBITDA | N2: 0.75 | O2: $1 = £0.75
B3: Mobility Payments & Enforcement | C3: PayPoint (PAY) | D3: LSE | E3: 337 | F3: 0.085 | G3: 351.3 | H3: 27 | I3: 84.8 | J3: =G3+H3 -> 378.3 | K3: =J3/E3 -> 1.1225519 | L3: =J3/I3 -> 4.4610849 | N3: 0.87 | O3: €1 = £0.87
C4: Byte Technology Group (BYIT) | D4: LSE | E4: 220.6 | F4: 0.007 | G4: 821.1 | H4: -96.6 | I4: 73.3 | J4: =G4+H4 -> 724.5 | K4: =J4/E4 -> 3.2842248 | L4: =J4/I4 -> 9.8840382
C5: Segment Average | D5: - | E5: - | F5: - | G5: - | H5: - | I5: - | J5: - | K5: =AVERAGE(K3:K4) -> 2.2033884 | L5: =AVERAGE(L3:L4) -> 7.1725616
B6: B2B Fleet & Automotive SaaS | C6: Vianet Group (VNET) | D6: LSE | E6: 15 | F6: -0.001 | G6: 19.2 | H6: -0.4 | I6: 3.9 | J6: =G6+H6 -> 18.8 | K6: =J6/E6 -> 1.2533333 | L6: =J6/I6 -> 4.8205128
C7: Verra Mobility (VRRM) | D7: NASDAQ | E7: =1025*$N$2 -> 768.75 | F7: 0.001 | G7: =723*$N$2 -> 542.25 | H7: 1017 | I7: =362.8*$N$2 -> 272.1 | J7: =G7+H7 -> 1559.25 | K7: =J7/E7 -> 2.0282927 | L7: =J7/I7 -> 5.73043
C8: Descartes Systems (DSGX) | D8: NASDAQ | E8: =753.9*$N$2 -> 565.425 | F8: 0.128 | G8: =6120*$N$2 -> 4590 | H8: -370 | I8: =319.7*$N$2 -> 239.775 | J8: =G8+H8 -> 4220 | K8: =J8/E8 -> 7.4634125 | L8: =J8/I8 -> 17.599833
C9: Segment Average | D9: - | E9: - | F9: - | G9: - | H9: - | I9: - | J9: - | K9: =AVERAGE(K7:K8) -> 4.7458526 | L9: =AVERAGE(L7:L8) -> 11.665132
B10: EV infrastracture | C10: Alfen Beheer (ALFEN) | D10: AMS | E10: =435.6*$N$3 -> 378.972 | F10: -0.074 | G10: =333.5*$N$3 -> 290.145 | H10: 20.7 | I10: =26.5*$N$3 -> 23.055 | J10: =G10+H10 -> 310.845 | K10: =J10/E10 -> 0.8202321 | L10: =J10/I10 -> 13.482759
C11: Segment Average | D11: - | E11: - | F11: - | G11: - | H11: - | I11: - | J11: - | K11: =K10 -> 0.8202321 | L11: =L10 -> 13.482759
B25: Notes to self - reason why each comparable is relevant

Sheet Valuation Summary
B2: Valuation & Levarage Summary Dashboard
B4: Segment | C4: Target Company | D4: EBITDA (£m) | E4: Target Multiple (Acquisition x) | F4: Purchase Enterprise Value (£m) | G4: Public Peer Multiple (EBITDA x) | H4: Implied Public Market Value (£m) | I4: Valuation Arbitrage (£m)
B5: Mobility Payments & Enforcement | C5: ParkingEye | D5: ='Target Financials'!E3/1000000 -> 28.78 | E5: 6.00x | F5: =D5*6 -> 172.68 | G5: =CCA!L5 -> 7.1725616 | H5: =D5*G5 -> 206.42632 | I5: =H5-F5 -> 33.746321
C6: TMA Group | D6: ='Target Financials'!E4/1000000 -> 7.417435 | E6: 6.00x | F6: =D6*6 -> 44.50461 | G6: =CCA!L5 -> 7.1725616 | H6: =D6*G6 -> 53.202009 | I6: =H6-F6 -> 8.6973991
B7: B2B Fleet & Automotive SaaS | C7: Yellow Line Parking (AppyWay) | D7: ='Target Financials'!E5/1000000 -> -0.05 | E7: 6.00x | F7: =D7*6 -> -0.3 | G7: =CCA!L9 -> 11.665132 | H7: =D7*G7 -> -0.58325658 | I7: =H7-F7 -> -0.28325658
C8: Ebbon Group | D8: ='Target Financials'!E6/1000000 -> 3.261578 | E8: 6.00x | F8: =D8*6 -> 19.569468 | G8: =CCA!L9 -> 11.665132 | H8: =D8*G8 -> 38.046737 | I8: =H8-F8 -> 18.477269
C9: FleetCheck | D9: ='Target Financials'!E7/1000000 -> 1.35 | E9: 6.00x | F9: =D9*6 -> 8.1 | G9: =CCA!L9 -> 11.665132 | H9: =D9*G9 -> 15.747928 | I9: =H9-F9 -> 7.6479276
B10: EV infrastracture | C10: Joju Charging | D10: ='Target Financials'!E8/1000000 -> 0.232206 | E10: 6.00x | F10: =D10*6 -> 1.393236 | G10: =CCA!L11 -> 13.482759 | H10: =D10*G10 -> 3.1307774 | I10: =H10-F10 -> 1.7375414
B11: Portfolio Total | D11: =SUM(D5:D10) -> 40.991219 | F11: =SUM(F5:F10) -> 245.94731 | H11: =SUM(H5:H10) -> 315.97052 | I11: =SUM(I5:I10) -> 70.023202
B15: Note: Public peer trading multiples are currently compressed across mid-market tech and B2B SaaS. While index performance appears strong this is concentrated amongst semiconductor and AI infrastructure winners. Excluding these outliers
B16: the wider market is experiencing depressed valuations. Hence the current target mutliples are very conserative and we can expect substantial long term multiple expansion.
B18: Debt Capacity & Sizing Analysis
B20: Bank Lending Assuptions
B21: Max Leverage Rule | C21: 3.5
B22: Bank Interest Rate | C22: 0.07
B23: Debt Term (years) | C23: 5
B24: Max Debt Capacity (£m) (Leverage Method) | D24: =D11*C21 -> 143.46927
B25: Annual Interest Expense (£m) | C25: =D24*C22 -> 10.042849
B26: Implied DSCR | C26: =D11/C25 -> 4.0816327
